setup.py
RE_3/__init__.py
RE_3_stuff.egg-info/PKG-INFO
RE_3_stuff.egg-info/SOURCES.txt
RE_3_stuff.egg-info/dependency_links.txt
RE_3_stuff.egg-info/requires.txt
RE_3_stuff.egg-info/top_level.txt
bin/RE_3_file.py
bin/config.py
bin/stats.py
bin/zombie_combat.py